gserp_api/__init__.py
gserp_api/search.py
gserp_api-0.1.7.dist-info/LICENSE
gserp_api-0.1.7.dist-info/METADATA
gserp_api-0.1.7.dist-info/WHEEL
gserp_api-0.1.7.dist-info/top_level.txt
gserp_api-0.1.7.dist-info/RECORD
