Metadata-Version: 2.1
Name: gserp_api
Version: 0.1.7
Summary: Open Source Google SERP API
Home-page: https://github.com/rushout09/gserp-api
Author: Rushabh Agarwal
Author-email: rushabh.agarwal9@gmail.com
Classifier: Programming Language :: Python :: 3
Classifier: License :: OSI Approved :: MIT License
Classifier: Operating System :: OS Independent
Requires-Python: >=3.6
License-File: LICENSE
Requires-Dist: beautifulsoup4==4.12.3
Requires-Dist: boto3==1.35.76
Requires-Dist: requests==2.32.3
Requires-Dist: requests-ip-rotator==1.0.14
